pythoncodliver/__init__.py
pythoncodliver/common.py
pythoncodliver/pythoncodliver.py
pythoncodliver-0.0.1.dist-info/LICENSE
pythoncodliver-0.0.1.dist-info/METADATA
pythoncodliver-0.0.1.dist-info/WHEEL
pythoncodliver-0.0.1.dist-info/entry_points.txt
pythoncodliver-0.0.1.dist-info/top_level.txt
pythoncodliver-0.0.1.dist-info/RECORD
